octopus_sensing_processing/__init__.py
octopus_sensing_processing/main.py
octopus_sensing_processing/octopus_sensing_client.py
octopus_sensing_processing/result_endpoint.py
octopus_sensing_processing/result_streaming.py
octopus_sensing_processing/test_result.py
octopus_sensing_processing-1.0.5.dist-info/LICENSE
octopus_sensing_processing-1.0.5.dist-info/METADATA
octopus_sensing_processing-1.0.5.dist-info/WHEEL
octopus_sensing_processing-1.0.5.dist-info/entry_points.txt
octopus_sensing_processing-1.0.5.dist-info/RECORD
