Metadata-Version: 2.1
Name: octopus-sensing-processing
Version: 1.0.5
Summary: Web base data processing for https://octopus-sensing.nastaran-saffar.me
Home-page: https://github.com/octopus-sensing/octopus-sensing-processing
License: GPL-3.0-or-later
Author: Nastaran Saffaryazdi
Author-email: nsaffar@gmail.com
Requires-Python: >=3.7,<4.0
Classifier: License :: OSI Approved :: GNU General Public License v3 or later (GPLv3+)
Classifier: Programming Language :: Python :: 3
Classifier: Programming Language :: Python :: 3.7
Classifier: Programming Language :: Python :: 3.8
Classifier: Programming Language :: Python :: 3.9
Classifier: Programming Language :: Python :: 3.10
Classifier: Programming Language :: Python :: 3.11
Classifier: Programming Language :: Python :: 3.12
Requires-Dist: CherryPy (>=18.6.0,<19.0.0)
Requires-Dist: numpy (>=1.21.0,<2.0.0)
Project-URL: Repository, https://github.com/octopus-sensing/octopus-sensing-processing
